Metadata-Version: 2.1
Name: tsatsu-mail-sender
Version: 0.0.6
Summary: A package to send emails and attachments
Home-page: https://github.com/edwardtsatsu/email_lib
Author: Akorlie Edward Tsatsu
Author-email: edwardakorlie73@gmail.com
License: MIT
Keywords: email
Classifier: Development Status :: 5 - Production/Stable
Classifier: Intended Audience :: Education
Classifier: Operating System :: Microsoft :: Windows :: Windows 10
Classifier: License :: OSI Approved :: MIT License
Classifier: Programming Language :: Python :: 3
